ceo_framework/__init__.py
ceo_framework/ceo_core.py
ceo_framework/conditions.py
ceo_framework/transformations.py
ceo_framework/utils.py
ceo_framework-0.1.8.dist-info/METADATA
ceo_framework-0.1.8.dist-info/WHEEL
ceo_framework-0.1.8.dist-info/top_level.txt
ceo_framework-0.1.8.dist-info/RECORD
