Metadata-Version: 2.1
Name: ceo-framework
Version: 0.1.8
Summary: Conditional Equality Operator Framework for conditional transformations in Python
Home-page: https://github.com/MASAGDT/ceo_framework
Author: Eric D. McCullar
Author-email: MASAGDT@gmail.com
Classifier: Programming Language :: Python :: 3
Classifier: License :: OSI Approved :: MIT License
Classifier: Operating System :: OS Independent
Requires-Python: >=3.6
Requires-Dist: numpy
Requires-Dist: Pillow
Requires-Dist: joblib
